senhasegura/__init__.py
senhasegura/modules/__init__.py
senhasegura/modules/a2a.py
senhasegura/utils/__init__.py
senhasegura/utils/auth.py
senhasegura-0.1.3.dist-info/LICENSE
senhasegura-0.1.3.dist-info/METADATA
senhasegura-0.1.3.dist-info/WHEEL
senhasegura-0.1.3.dist-info/RECORD
