Metadata-Version: 2.1
Name: senhasegura
Version: 0.1.3
Summary:  An unofficial module for integrating with SenhaSegura APIs, supporting OAuth1 and OAuth2 authentication. It offers a simple interface for making HTTP requests while ensuring hostname and endpoint validation. Ideal for developers looking to implement password management functionalities securely.
License: MIT
Keywords: senhasegura,api,integration,a2a
Author: Ricardo Castro
Author-email: srrenks@gmail.com
Requires-Python: >=3.8,<4.0
Classifier: License :: OSI Approved :: MIT License
Classifier: Programming Language :: Python :: 3
Classifier: Programming Language :: Python :: 3.8
Classifier: Programming Language :: Python :: 3.9
Classifier: Programming Language :: Python :: 3.10
Classifier: Programming Language :: Python :: 3.11
Classifier: Programming Language :: Python :: 3.12
Requires-Dist: requests (>=2.24.0,<3.0.0)
Requires-Dist: requests_oauthlib (>=1.3.0,<2.0.0)
